[
    {
        "Age": "29",
        "College": "--",
        "Height": "6'10\"",
        "Name": "Davis",
        "Number": "44",
        "Position": "SF",
        "Salary": "$16000000",
        "Surname": "Bertans",
        "Weight": "225lbs"
    },
    {
        "Age": "27",
        "College": "SMU",
        "Height": "6'5\"",
        "Name": "Sterling",
        "Number": "0",
        "Position": "SF",
        "Salary": "$3000000",
        "Surname": "Brown",
        "Weight": "219lbs"
    },
    {
        "Age": "25",
        "College": "Villanova",
        "Height": "6'1\"",
        "Name": "Jalen",
        "Number": "13",
        "Position": "PG",
        "Salary": "$1802057",
        "Surname": "Brunson",
        "Weight": "190lbs"
    },
    {
        "Age": "31",
        "College": "NorthCarolina",
        "Height": "6'6\"",
        "Name": "Reggie",
        "Number": "25",
        "Position": "SF",
        "Salary": "$9536000",
        "Surname": "Bullock",
        "Weight": "205lbs"
    },
    {
        "Age": "29",
        "College": "185lbs",
        "Height": "6'",
        "Name": "Trey",
        "Number": "3",
        "Position": "PG",
        "Salary": "Michigan",
        "Surname": "Burke",
        "Weight": "0\""
    },
    {
        "Age": "24",
        "College": "Washington",
        "Height": "6'9\"",
        "Name": "Marquese",
        "Number": "32",
        "Position": "SF",
        "Salary": "$958529",
        "Surname": "Chriss",
        "Weight": "240lbs"
    },
    {
        "Age": "29",
        "College": "Colorado",
        "Height": "6'6\"",
        "Name": "Spencer",
        "Number": "26",
        "Position": "PG",
        "Salary": "$17142857",
        "Surname": "Dinwiddie",
        "Weight": "215lbs"
    },
    {
        "Age": "23",
        "College": "--",
        "Height": "6'7\"",
        "Name": "Luka",
        "Number": "77",
        "Position": "PG",
        "Salary": "$10174391",
        "Surname": "Doncic",
        "Weight": "230lbs"
    },
    {
        "Age": "29",
        "College": "Florida",
        "Height": "6'7\"",
        "Name": "Dorian",
        "Number": "10",
        "Position": "PF",
        "Salary": "$4000000",
        "Surname": "Finney-Smith",
        "Weight": "220lbs"
    },
    {
        "Age": "21",
        "College": "Arizona",
        "Height": "6'5\"",
        "Name": "Josh",
        "Number": "8",
        "Position": "SG",
        "Salary": "$2957520",
        "Surname": "Green",
        "Weight": "200lbs"
    },
    {
        "Age": "30",
        "College": "Michigan",
        "Height": "6'5\"",
        "Name": "Tim",
        "Number": "11",
        "Position": "SF",
        "Salary": "$21308816",
        "Surname": "Hardaway",
        "Weight": "205lbs"
    },
    {
        "Age": "30",
        "College": "--",
        "Height": "6'10\"",
        "Name": "Maxi",
        "Number": "42",
        "Position": "PF",
        "Salary": "$8975000",
        "Surname": "Kleber",
        "Weight": "240lbs"
    },
    {
        "Age": "30",
        "College": "Kentucky",
        "Height": "6'2\"",
        "Name": "Brandon",
        "Number": "20",
        "Position": "PG",
        "Salary": "$1000",
        "Surname": "Knight",
        "Weight": "182lbs"
    },
    {
        "Age": "33",
        "College": "--",
        "Height": "7'3\"",
        "Name": "Boban",
        "Number": "51",
        "Position": "C",
        "Salary": "$3500000",
        "Surname": "Marjanovic",
        "Weight": "290lbs"
    },
    {
        "Age": "23",
        "College": "--",
        "Height": "6'4\"",
        "Name": "Frank",
        "Number": "21",
        "Position": "PG",
        "Salary": "$1669178",
        "Surname": "Ntilikina",
        "Weight": "200lbs"
    },
    {
        "Age": "26",
        "College": "NorthCarolina",
        "Height": "6'5\"",
        "Name": "Theo",
        "Number": "1",
        "Position": "G",
        "Salary": "$1000",
        "Surname": "Pinson",
        "Weight": "212lbs"
    },
    {
        "Age": "30",
        "College": "Stanford",
        "Height": "6'10\"",
        "Name": "Dwight",
        "Number": "7",
        "Position": "C",
        "Salary": "$11080125",
        "Surname": "Powell",
        "Weight": "240lbs"
    },
    {
        "Age": "23",
        "College": "GeorgiaTech",
        "Height": "6'8\"",
        "Name": "Moses",
        "Number": "5",
        "Position": "F",
        "Salary": "$100",
        "Surname": "Wright",
        "Weight": "226lbs"
    }
]